obspy/.coveragerc
obspy/CONTRIBUTORS.txt
obspy/LICENSE.txt
obspy/RELEASE-VERSION
obspy/__init__.py
obspy/conftest.py
obspy/pytest.ini
obspy/clients/__init__.py
obspy/clients/base.py
obspy/clients/httpproxy.py
obspy/clients/earthworm/README.txt
obspy/clients/earthworm/__init__.py
obspy/clients/earthworm/client.py
obspy/clients/earthworm/waveserver.py
obspy/clients/earthworm/tests/__init__.py
obspy/clients/earthworm/tests/test_client.py
obspy/clients/fdsn/README.txt
obspy/clients/fdsn/__init__.py
obspy/clients/fdsn/client.py
obspy/clients/fdsn/header.py
obspy/clients/fdsn/wadl_parser.py
obspy/clients/fdsn/mass_downloader/__init__.py
obspy/clients/fdsn/mass_downloader/domain.py
obspy/clients/fdsn/mass_downloader/download_helpers.py
obspy/clients/fdsn/mass_downloader/mass_downloader.py
obspy/clients/fdsn/mass_downloader/restrictions.py
obspy/clients/fdsn/mass_downloader/utils.py
obspy/clients/fdsn/routing/__init__.py
obspy/clients/fdsn/routing/eidaws_routing_client.py
obspy/clients/fdsn/routing/federator_routing_client.py
obspy/clients/fdsn/routing/routing_client.py
obspy/clients/fdsn/tests/__init__.py
obspy/clients/fdsn/tests/test_base_routing_client.py
obspy/clients/fdsn/tests/test_client.py
obspy/clients/fdsn/tests/test_eidaws_routing_client.py
obspy/clients/fdsn/tests/test_federator_routing_client.py
obspy/clients/fdsn/tests/test_mass_downloader.py
obspy/clients/fdsn/tests/test_wadl_parser.py
obspy/clients/fdsn/tests/data/2014-01-07_ethz_dataselect.wadl
obspy/clients/fdsn/tests/data/2014-01-07_ethz_event.wadl
obspy/clients/fdsn/tests/data/2014-01-07_ethz_station.wadl
obspy/clients/fdsn/tests/data/2014-01-07_iris_dataselect.wadl
obspy/clients/fdsn/tests/data/2014-01-07_iris_event.wadl
obspy/clients/fdsn/tests/data/2014-01-07_iris_station.wadl
obspy/clients/fdsn/tests/data/2014-01-07_ncedc_dataselect.wadl
obspy/clients/fdsn/tests/data/2014-01-07_ncedc_event.wadl
obspy/clients/fdsn/tests/data/2014-01-07_ncedc_station.wadl
obspy-1.4.2.dist-info/METADATA
obspy-1.4.2.dist-info/WHEEL
obspy-1.4.2.dist-info/entry_points.txt
obspy-1.4.2.dist-info/namespace_packages.txt
obspy-1.4.2.dist-info/top_level.txt
obspy-1.4.2.dist-info/RECORD
obspy-1.4.2.dist-info/licenses/LICENSE.txt
