Metadata-Version: 2.4
Name: obspy
Version: 1.4.2
Summary: ObsPy - a Python framework for seismological observatories.
Home-page: https://www.obspy.org
Author: The ObsPy Development Team
Author-email: devs@obspy.org
License: GNU Lesser General Public License, Version 3 (LGPLv3)
Project-URL: Bug Tracker, https://github.com/obspy/obspy/issues
Project-URL: Documentation, https://docs.obspy.org/
Project-URL: Source Code, https://github.com/obspy/obspy
Keywords: ALSEP,ArcLink,array,array analysis,ASC,beachball,beamforming,cross correlation,database,dataless,Dataless SEED,DMX,earthquakes,Earthworm,EIDA,envelope,ESRI,events,FDSN,features,filter,focal mechanism,FOCMEC,GCF,GSE1,GSE2,hob,Tau-P,IASPEI,imaging,IMS,instrument correction,instrument simulation,IRIS,ISF,kinemetrics,KML,magnitude,MiniSEED,misfit,mopad,MSEED,NDK,NERA,NERIES,NonLinLoc,NLLOC,Nordic,NRL,observatory,ORFEUS,PDAS,picker,processing,PQLX,Q,real time,realtime,REFTEK,REFTEK130,RG-1.
Platform: OS Independent
Classifier: Development Status :: 5 - Production/Stable
Classifier: Environment :: Console
Classifier: Intended Audience :: Science/Research
Classifier: Intended Audience :: Developers
Classifier: License :: OSI Approved :: GNU Lesser General Public License v3 (LGPLv3)
Classifier: Operating System :: OS Independent
Classifier: Programming Language :: Python
Classifier: Programming Language :: Python :: 3
Classifier: Programming Language :: Python :: 3.8
Classifier: Programming Language :: Python :: 3.9
Classifier: Programming Language :: Python :: 3.10
Classifier: Programming Language :: Python :: 3.11
Classifier: Programming Language :: Python :: 3.12
Classifier: Topic :: Scientific/Engineering
Classifier: Topic :: Scientific/Engineering :: Physics
Requires-Python: >=3.8
License-File: LICENSE.txt
Requires-Dist: numpy>=1.20
Requires-Dist: scipy>=1.7
Requires-Dist: matplotlib>=3.3
Requires-Dist: lxml
Requires-Dist: setuptools
Requires-Dist: sqlalchemy<2
Requires-Dist: decorator
Requires-Dist: requests
Provides-Extra: tests
Requires-Dist: packaging; extra == "tests"
Requires-Dist: pyproj; extra == "tests"
Requires-Dist: pytest; extra == "tests"
Requires-Dist: pytest-json-report; extra == "tests"
Provides-Extra: geo
Requires-Dist: geographiclib; extra == "geo"
Provides-Extra: imaging
Requires-Dist: cartopy; extra == "imaging"
Provides-Extra: io-shapefile
Requires-Dist: pyshp; extra == "io-shapefile"
Provides-Extra: all
Requires-Dist: packaging; extra == "all"
Requires-Dist: pyproj; extra == "all"
Requires-Dist: pytest; extra == "all"
Requires-Dist: pytest-json-report; extra == "all"
Requires-Dist: geographiclib; extra == "all"
Requires-Dist: cartopy; extra == "all"
Requires-Dist: pyshp; extra == "all"
Dynamic: author
Dynamic: author-email
Dynamic: classifier
Dynamic: description
Dynamic: home-page
Dynamic: keywords
Dynamic: license
Dynamic: license-file
Dynamic: platform
Dynamic: project-url
Dynamic: provides-extra
Dynamic: requires-dist
Dynamic: requires-python
Dynamic: summary
